{
  "type": "eternalores:config_ore_feature",
  "config": {
    "ore": "eternalores:zinc_mining",
    "targets": [
      {
        "state": {
          "Name": "eternalores:zinc_ore_block"
        },
        "target": {
          "block": "minecraft:stone",
          "predicate_type": "minecraft:block_match"
        }
      },
      {
        "state": {
          "Name": "eternalores:deepslate_zinc_ore_block"
        },
        "target": {
          "block": "minecraft:deepslate",
          "predicate_type": "minecraft:block_match"
        }
      }
    ]
  }
}